{
  "id": "taliban-camp-david",
  "title": "Taliban Camp David Invitation",
  "primaryCategory": "character",
  "severity": "concerning",
  "timeline": "first-term",
  "date": "2019-09-07",
  "summary": "Trump invited Taliban leaders to Camp David for peace talks just days before 18th anniversary of 9/11. Taliban responsible for harboring al-Qaeda before 9/11 attacks. Meeting canceled after Taliban claimed responsibility for attack killing US soldier. Rep. Liz Cheney: 'Camp David is where America's leaders met to plan our response to the 9/11 terrorist attacks.'",
  "keyFacts": [
    "Trump invited Taliban leaders to Camp David for peace talks",
    "Planned meeting scheduled for September 8, 2019 - just days before 18th anniversary of 9/11",
    "Taliban responsible for harboring al-Qaeda before 9/11 attacks",
    "Meeting canceled after Taliban claimed responsibility for attack killing US soldier",
    "Rep. Liz Cheney: 'Camp David is where America's leaders met to plan our response to the 9/11 terrorist attacks'"
  ],
  "sources": [
    {
      "text": "CNN: Trump overruled advisers, VP on Taliban Camp David meeting",
      "url": "https://www.cnn.com/2019/09/09/politics/camp-david-donald-trump-mike-pence-taliban/index.html",
      "type": "news"
    },
    {
      "text": "ABC News: Trump cancels secret meeting with the Taliban at Camp David after deadly bombings",
      "url": "https://abcnews.go.com/Politics/president-trump-cancels-secret-meeting-taliban-camp-david/story?id=65465259",
      "type": "news"
    },
    {
      "text": "NPR: At Camp David, Trump Sought The Mantle Of History. But Afghanistan Is Different",
      "url": "https://www.npr.org/2019/09/10/759268550/at-camp-david-trump-sought-the-mantle-of-history-but-afghanistan-is-different",
      "type": "analysis"
    },
    {
      "text": "NBC News: Pompeo defends plan to host Taliban leaders at Camp David",
      "url": "https://www.nbcnews.com/politics/donald-trump/pompeo-defends-plan-host-taliban-leaders-camp-david-n1051211",
      "type": "news"
    }
  ],
  "specialTags": ["foreign-policy", "terrorism", "afghanistan"]
}
